{
  "adpe": null,
  "adpf": null,
  "ap": null,
  "comment": "#G1186",
  "conversions": [
    {
      "to": "KG",
      "value": 35.2
    }
  ],
  "cru": null,
  "declared_unit": "M2",
  "eee": null,
  "eet": null,
  "ep": null,
  "format_version": "0.3.0",
  "fw": null,
  "gwp": {
    "a1a3": 45.7,
    "a4": null,
    "a5": null,
    "b1": null,
    "b2": null,
    "b3": null,
    "b4": null,
    "b5": null,
    "b6": null,
    "b7": null,
    "c1": null,
    "c2": null,
    "c3": 42.5,
    "c4": 0.18,
    "d": -37.1
  },
  "hwd": null,
  "id": "7e7523e5-c203-5c94-8920-417f4ef50491",
  "location": "DK",
  "mer": null,
  "meta_data": null,
  "mrf": null,
  "name": "Ovenlyskuppel, plast (komplet ovenlys)",
  "nhwd": null,
  "nrsf": null,
  "odp": null,
  "penre": null,
  "penrm": null,
  "penrt": null,
  "pere": null,
  "perm": null,
  "pert": null,
  "pocp": null,
  "published_date": "2020-12-22T00:00:00",
  "reference_service_life": null,
  "rsf": null,
  "rwd": null,
  "sm": null,
  "source": {
    "name": "BR18 - Tabel 7",
    "url": "http://www.oekobaudat.de/OEKOBAU.DAT/resource/processes/2bf377b2-7923-4e05-b7a0-3c02e63d3476?version=00.00.007"
  },
  "standard": "EN15804A1",
  "subtype": "Generic",
  "valid_until": "2025-12-22T00:00:00",
  "version": "version 2 - 201222"
}